whdtj_testing/__init__.py
whdtj_testing/whdtj_testing.py
whdtj_test_module-0.1.dist-info/METADATA
whdtj_test_module-0.1.dist-info/WHEEL
whdtj_test_module-0.1.dist-info/top_level.txt
whdtj_test_module-0.1.dist-info/RECORD
